Constants/ActionConstants.py
Constants/SyncConstants.py
Constants/ValidationConstants.py
Constants/__init__.py
Main/FrameWorkMain.py
Main/__init__.py
PerformActions/Action.py
PerformActions/Synchronisation.py
PerformActions/Validation.py
PerformActions/__init__.py
Utils/AzureHelper.py
Utils/CSVHelper.py
Utils/DateTimeHelper.py
Utils/DbHelper.py
Utils/XMLHelper.py
Utils/__init__.py
pytestframework-1.4.dist-info/METADATA
pytestframework-1.4.dist-info/WHEEL
pytestframework-1.4.dist-info/top_level.txt
pytestframework-1.4.dist-info/RECORD
