Metadata-Version: 2.1
Name: pytestframework
Version: 1.4
Summary: Pytest framework project
Author: Yogesh C
Author-email: Ykotha@munichre.digital
Requires-Dist: pytest>=7.4.4
Requires-Dist: playwright>=1.40.0
